winrt/_winrt_windows_media_capture.cp314-win_amd64.pyd
winrt/_winrt_windows_media_capture.pyi
winrt/windows/media/capture/__init__.py
winrt/windows/media/capture/py.typed
winrt_windows_media_capture-3.2.1.dist-info/METADATA
winrt_windows_media_capture-3.2.1.dist-info/WHEEL
winrt_windows_media_capture-3.2.1.dist-info/top_level.txt
winrt_windows_media_capture-3.2.1.dist-info/RECORD
